moveread/tatr/__init__.py
moveread/tatr/__init__.pyi
moveread/tatr/config.py
moveread/tatr/data.py
moveread/tatr/decoding.py
moveread/tatr/model.py
moveread/tatr/sorting.py
moveread_tatr-0.1.6.dist-info/METADATA
moveread_tatr-0.1.6.dist-info/WHEEL
moveread_tatr-0.1.6.dist-info/top_level.txt
moveread_tatr-0.1.6.dist-info/RECORD
