Metadata-Version: 2.1
Name: moveread-tatr
Version: 0.1.6
Summary: Moveread Table Transformer model
Author-email: Marcel Claramunt <marcel@moveread.com>
Project-URL: repo, https://github.com/moveread/table-transformer.git
Requires-Python: >=3.10
Requires-Dist: torch
Requires-Dist: transformers==4.45.2
Requires-Dist: haskellian
Requires-Dist: pure-cv
Requires-Dist: torchvision
Requires-Dist: scipy
